CHANGES.rst
LICENSE
MANIFEST.in
README
README.rst
requirements.txt
setup.py
rogue_scores/__init__.py
rogue_scores/cli.py
rogue_scores/scores.py
rogue_scores/upload.py
rogue_scores.egg-info/PKG-INFO
rogue_scores.egg-info/SOURCES.txt
rogue_scores.egg-info/dependency_links.txt
rogue_scores.egg-info/entry_points.txt
rogue_scores.egg-info/requires.txt
rogue_scores.egg-info/top_level.txt
rogue_scores/web/templates/main.html