Metadata-Version: 1.1
Name: rogue-scores
Version: 0.0.7
Summary: online Rogue scores leaderboard
Home-page: https://github.com/bfontaine/rogue_scores
Author: Baptiste Fontaine
Author-email: b@ptistefontaine.fr
License: Copyright © 2014 – Baptiste Fontaine
